unmhtml/__init__.py
unmhtml/converter.py
unmhtml/parser.py
unmhtml/processor.py
unmhtml/py.typed
unmhtml/regex_utils.py
unmhtml/security.py
unmhtml-0.2.0.dist-info/METADATA
unmhtml-0.2.0.dist-info/WHEEL
unmhtml-0.2.0.dist-info/licenses/LICENSE
unmhtml-0.2.0.dist-info/RECORD
