Metadata-Version: 2.4
Name: unmhtml
Version: 0.2.0
Summary: MHTML to HTML converter library using Python stdlib
Author: Johan Schuijt
License: MIT
License-File: LICENSE
Keywords: archive,converter,html,mhtml,mime,web
Classifier: Development Status :: 3 - Alpha
Classifier: Intended Audience :: Developers
Classifier: License :: OSI Approved :: MIT License
Classifier: Programming Language :: Python :: 3
Classifier: Programming Language :: Python :: 3.8
Classifier: Programming Language :: Python :: 3.9
Classifier: Programming Language :: Python :: 3.10
Classifier: Programming Language :: Python :: 3.11
Classifier: Programming Language :: Python :: 3.12
Classifier: Topic :: Internet :: WWW/HTTP
Classifier: Topic :: Software Development :: Libraries :: Python Modules
Classifier: Topic :: Text Processing :: Markup :: HTML
Requires-Python: >=3.8
Provides-Extra: test
Requires-Dist: pytest-cov; extra == 'test'
Requires-Dist: pytest>=6.0; extra == 'test'
